venvat/__init__.py
venvat/venvat_runner.py
venvat-1.0.0.data/scripts/venvat.ps1
venvat-1.0.0.dist-info/LICENSE
venvat-1.0.0.dist-info/METADATA
venvat-1.0.0.dist-info/WHEEL
venvat-1.0.0.dist-info/entry_points.txt
venvat-1.0.0.dist-info/top_level.txt
venvat-1.0.0.dist-info/RECORD
