Metadata-Version: 2.1
Name: venvat
Version: 1.0.0
Summary: A script to activate Python virtual environments.
Home-page: https://github.com/Kelocker/venvat.git
Author: Kelocker
Author-email: thekelvin0fficials@gmail.com
License: MIT
Project-URL: Homepage, https://github.com/Kelocker/venvat.git
Project-URL: Issues, https://github.com/Kelocker/venvat.git/issues
Classifier: Programming Language :: Python :: 3
Classifier: License :: OSI Approved :: MIT License
Classifier: Operating System :: OS Independent
License-File: LICENSE
